{
  "configs": [
    {
      "categories": [
        {
          "width": 455,
          "height": 75,
          "hero_ids": [
            8,
            70,
            1,
            49,
            72,
            53,
            46
          ],
          "x_position": 0,
          "y_position": 0,
          "category_name": "Carry"
        },
        {
          "width": 455,
          "height": 75,
          "hero_ids": [
            39,
            13,
            74,
            17,
            52,
            106,
            53
          ],
          "x_position": 0,
          "y_position": 95,
          "category_name": "Mid"
        },
        {
          "width": 455,
          "height": 75,
          "hero_ids": [
            129,
            98,
            2,
            104,
            28,
            135,
            96
          ],
          "x_position": 0,
          "y_position": 190,
          "category_name": "Offlane"
        },
        {
          "width": 455,
          "height": 75,
          "hero_ids": [
            128,
            86,
            71,
            14,
            101,
            26,
            21
          ],
          "x_position": 0,
          "y_position": 285,
          "category_name": "Support"
        },
        {
          "width": 455,
          "height": 75,
          "hero_ids": [
            87,
            64,
            26,
            75,
            14,
            31,
            128
          ],
          "x_position": 0,
          "y_position": 380,
          "category_name": "Hard Support"
        },
        {
          "width": 600,
          "height": 600,
          "hero_ids": [
            102,
            73,
            68,
            1,
            113,
            2,
            3,
            65,
            38,
            4,
            62,
            78,
            99,
            61,
            96,
            81,
            66,
            56,
            51,
            5,
            55,
            119,
            135,
            50,
            43,
            87,
            69,
            49,
            6,
            107,
            7,
            103,
            106,
            58,
            33,
            41,
            121,
            72,
            123,
            59,
            74,
            91,
            64,
            8,
            90,
            145,
            23,
            104,
            52,
            31,
            54,
            25,
            26,
            80,
            48,
            77,
            97,
            136,
            129,
            94,
            82,
            9,
            114,
            10,
            138,
            89,
            53,
            36,
            60,
            88,
            84,
            57,
            111,
            76,
            120,
            44,
            12,
            110,
            137,
            13,
            14,
            45,
            39,
            15,
            32,
            131,
            86,
            16,
            79,
            11,
            27,
            75,
            101,
            28,
            93,
            128,
            35,
            67,
            71,
            17,
            18,
            105,
            46,
            109,
            29,
            98,
            34,
            19,
            83,
            95,
            100,
            108,
            85,
            70,
            20,
            40,
            47,
            92,
            126,
            37,
            63,
            21,
            112,
            30,
            42,
            22
          ],
          "x_position": 500,
          "y_position": 0,
          "category_name": "All Heroes"
        }
      ],
      "config_name": "Dota2ProTracker 7.39e - All Roles"
    },
    {
      "categories": [
        {
          "width": 65,
          "height": 525,
          "hero_ids": [
            8,
            70,
            1,
            49,
            72,
            53,
            46
          ],
          "x_position": 0,
          "y_position": 0,
          "category_name": "Top Heroes Pos 1"
        },
        {
          "width": 280,
          "height": 55,
          "hero_ids": [
            40,
            52,
            31,
            14,
            26,
            96,
            87
          ],
          "x_position": 75,
          "y_position": 20,
          "category_name": "Best with"
        },
        {
          "width": 280,
          "height": 55,
          "hero_ids": [
            2,
            43,
            42,
            64,
            145,
            99,
            136
          ],
          "x_position": 365,
          "y_position": 20,
          "category_name": "Worst with"
        },
        {
          "width": 280,
          "height": 55,
          "hero_ids": [
            72,
            64,
            86,
            14,
            129,
            17,
            53
          ],
          "x_position": 655,
          "y_position": 20,
          "category_name": "Best against"
        },
        {
          "width": 280,
          "height": 55,
          "hero_ids": [
            73,
            82,
            88,
            14,
            33,
            7,
            136
          ],
          "x_position": 945,
          "y_position": 20,
          "category_name": "Worst against"
        },
        {
          "width": 280,
          "height": 55,
          "hero_ids": [
            14,
            71,
            135,
            74,
            31,
            128,
            98
          ],
          "x_position": 75,
          "y_position": 95,
          "category_name": "Best with"
        },
        {
          "width": 280,
          "height": 55,
          "hero_ids": [
            22,
            86,
            53,
            35,
            64,
            120,
            34
          ],
          "x_position": 365,
          "y_position": 95,
          "category_name": "Worst with"
        },
        {
          "width": 280,
          "height": 55,
          "hero_ids": [
            123,
            86,
            128,
            94,
            64,
            98,
            11
          ],
          "x_position": 655,
          "y_position": 95,
          "category_name": "Best against"
        },
        {
          "width": 280,
          "height": 55,
          "hero_ids": [
            40,
            102,
            53,
            111,
            45,
            75,
            109
          ],
          "x_position": 945,
          "y_position": 95,
          "category_name": "Worst against"
        },
        {
          "width": 280,
          "height": 55,
          "hero_ids": [
            39,
            111,
            22,
            88,
            40,
            79,
            119
          ],
          "x_position": 75,
          "y_position": 170,
          "category_name": "Best with"
        },
        {
          "width": 280,
          "height": 55,
          "hero_ids": [
            5,
            26,
            11,
            71,
            13,
            129,
            14
          ],
          "x_position": 365,
          "y_position": 170,
          "category_name": "Worst with"
        },
        {
          "width": 280,
          "height": 55,
          "hero_ids": [
            22,
            119,
            53,
            101,
            34,
            20,
            112
          ],
          "x_position": 655,
          "y_position": 170,
          "category_name": "Best against"
        },
        {
          "width": 280,
          "height": 55,
          "hero_ids": [
            74,
            98,
            109,
            59,
            128,
            104,
            87
          ],
          "x_position": 945,
          "y_position": 170,
          "category_name": "Worst against"
        },
        {
          "width": 280,
          "height": 55,
          "hero_ids": [
            74,
            14,
            96,
            62,
            53,
            26,
            40
          ],
          "x_position": 75,
          "y_position": 245,
          "category_name": "Best with"
        },
        {
          "width": 280,
          "height": 55,
          "hero_ids": [
            51,
            86,
            38,
            64,
            7,
            45,
            27
          ],
          "x_position": 365,
          "y_position": 245,
          "category_name": "Worst with"
        },
        {
          "width": 280,
          "height": 55,
          "hero_ids": [
            137,
            45,
            101,
            7,
            40,
            11,
            17
          ],
          "x_position": 655,
          "y_position": 245,
          "category_name": "Best against"
        },
        {
          "width": 280,
          "height": 55,
          "hero_ids": [
            14,
            27,
            126,
            54,
            53,
            71,
            94
          ],
          "x_position": 945,
          "y_position": 245,
          "category_name": "Worst against"
        },
        {
          "width": 280,
          "height": 55,
          "hero_ids": [
            111,
            120,
            45,
            28,
            102,
            59,
            88
          ],
          "x_position": 75,
          "y_position": 320,
          "category_name": "Best with"
        },
        {
          "width": 280,
          "height": 55,
          "hero_ids": [
            11,
            75,
            64,
            7,
            86,
            37,
            52
          ],
          "x_position": 365,
          "y_position": 320,
          "category_name": "Worst with"
        },
        {
          "width": 280,
          "height": 55,
          "hero_ids": [
            86,
            93,
            38,
            11,
            51,
            18,
            45
          ],
          "x_position": 655,
          "y_position": 320,
          "category_name": "Best against"
        },
        {
          "width": 280,
          "height": 55,
          "hero_ids": [
            8,
            17,
            14,
            98,
            52,
            87,
            54
          ],
          "x_position": 945,
          "y_position": 320,
          "category_name": "Worst against"
        },
        {
          "width": 280,
          "height": 55,
          "hero_ids": [
            14,
            40,
            62,
            17,
            87,
            104,
            96
          ],
          "x_position": 75,
          "y_position": 395,
          "category_name": "Best with"
        },
        {
          "width": 280,
          "height": 55,
          "hero_ids": [
            5,
            21,
            120,
            64,
            129,
            11,
            97
          ],
          "x_position": 365,
          "y_position": 395,
          "category_name": "Worst with"
        },
        {
          "width": 280,
          "height": 55,
          "hero_ids": [
            75,
            64,
            10,
            26,
            96,
            54,
            2
          ],
          "x_position": 655,
          "y_position": 395,
          "category_name": "Best against"
        },
        {
          "width": 280,
          "height": 55,
          "hero_ids": [
            14,
            88,
            106,
            40,
            8,
            128,
            30
          ],
          "x_position": 945,
          "y_position": 395,
          "category_name": "Worst against"
        },
        {
          "width": 280,
          "height": 55,
          "hero_ids": [
            126,
            98,
            47,
            135,
            26,
            53,
            30
          ],
          "x_position": 75,
          "y_position": 470,
          "category_name": "Best with"
        },
        {
          "width": 280,
          "height": 55,
          "hero_ids": [
            51,
            120,
            38,
            100,
            68,
            74,
            86
          ],
          "x_position": 365,
          "y_position": 470,
          "category_name": "Worst with"
        },
        {
          "width": 280,
          "height": 55,
          "hero_ids": [
            1,
            7,
            54,
            18,
            129,
            26,
            72
          ],
          "x_position": 655,
          "y_position": 470,
          "category_name": "Best against"
        },
        {
          "width": 280,
          "height": 55,
          "hero_ids": [
            126,
            17,
            94,
            128,
            48,
            135,
            53
          ],
          "x_position": 945,
          "y_position": 470,
          "category_name": "Worst against"
        }
      ],
      "config_name": "Dota2ProTracker 7.39e - Carry"
    },
    {
      "categories": [
        {
          "width": 65,
          "height": 525,
          "hero_ids": [
            39,
            13,
            74,
            17,
            52,
            106,
            53
          ],
          "x_position": 0,
          "y_position": 0,
          "category_name": "Top Heroes Pos 2"
        },
        {
          "width": 280,
          "height": 55,
          "hero_ids": [
            8,
            45,
            87,
            26,
            7,
            104,
            109
          ],
          "x_position": 75,
          "y_position": 20,
          "category_name": "Best with"
        },
        {
          "width": 280,
          "height": 55,
          "hero_ids": [
            86,
            12,
            68,
            101,
            1,
            29,
            129
          ],
          "x_position": 365,
          "y_position": 20,
          "category_name": "Worst with"
        },
        {
          "width": 280,
          "height": 55,
          "hero_ids": [
            54,
            21,
            35,
            129,
            11,
            6,
            5
          ],
          "x_position": 655,
          "y_position": 20,
          "category_name": "Best against"
        },
        {
          "width": 280,
          "height": 55,
          "hero_ids": [
            104,
            40,
            126,
            106,
            87,
            14,
            101
          ],
          "x_position": 945,
          "y_position": 20,
          "category_name": "Worst against"
        },
        {
          "width": 280,
          "height": 55,
          "hero_ids": [
            102,
            22,
            87,
            98,
            14,
            63,
            62
          ],
          "x_position": 75,
          "y_position": 95,
          "category_name": "Best with"
        },
        {
          "width": 280,
          "height": 55,
          "hero_ids": [
            18,
            97,
            6,
            21,
            86,
            1,
            84
          ],
          "x_position": 365,
          "y_position": 95,
          "category_name": "Worst with"
        },
        {
          "width": 280,
          "height": 55,
          "hero_ids": [
            93,
            14,
            53,
            68,
            101,
            1,
            39
          ],
          "x_position": 655,
          "y_position": 95,
          "category_name": "Best against"
        },
        {
          "width": 280,
          "height": 55,
          "hero_ids": [
            40,
            59,
            126,
            53,
            10,
            71,
            14
          ],
          "x_position": 945,
          "y_position": 95,
          "category_name": "Worst against"
        },
        {
          "width": 280,
          "height": 55,
          "hero_ids": [
            40,
            14,
            31,
            135,
            2,
            70,
            8
          ],
          "x_position": 75,
          "y_position": 170,
          "category_name": "Best with"
        },
        {
          "width": 280,
          "height": 55,
          "hero_ids": [
            99,
            102,
            120,
            79,
            46,
            18,
            68
          ],
          "x_position": 365,
          "y_position": 170,
          "category_name": "Worst with"
        },
        {
          "width": 280,
          "height": 55,
          "hero_ids": [
            11,
            1,
            94,
            129,
            7,
            64,
            26
          ],
          "x_position": 655,
          "y_position": 170,
          "category_name": "Best against"
        },
        {
          "width": 280,
          "height": 55,
          "hero_ids": [
            50,
            28,
            128,
            88,
            40,
            14,
            8
          ],
          "x_position": 945,
          "y_position": 170,
          "category_name": "Worst against"
        },
        {
          "width": 280,
          "height": 55,
          "hero_ids": [
            88,
            53,
            128,
            48,
            60,
            8,
            102
          ],
          "x_position": 75,
          "y_position": 245,
          "category_name": "Best with"
        },
        {
          "width": 280,
          "height": 55,
          "hero_ids": [
            54,
            38,
            86,
            46,
            18,
            123,
            21
          ],
          "x_position": 365,
          "y_position": 245,
          "category_name": "Worst with"
        },
        {
          "width": 280,
          "height": 55,
          "hero_ids": [
            86,
            123,
            120,
            46,
            10,
            18,
            72
          ],
          "x_position": 655,
          "y_position": 245,
          "category_name": "Best against"
        },
        {
          "width": 280,
          "height": 55,
          "hero_ids": [
            126,
            7,
            8,
            49,
            87,
            75,
            104
          ],
          "x_position": 945,
          "y_position": 245,
          "category_name": "Worst against"
        },
        {
          "width": 280,
          "height": 55,
          "hero_ids": [
            87,
            14,
            101,
            8,
            104,
            135,
            26
          ],
          "x_position": 75,
          "y_position": 320,
          "category_name": "Best with"
        },
        {
          "width": 280,
          "height": 55,
          "hero_ids": [
            136,
            42,
            99,
            58,
            137,
            119,
            50
          ],
          "x_position": 365,
          "y_position": 320,
          "category_name": "Worst with"
        },
        {
          "width": 280,
          "height": 55,
          "hero_ids": [
            7,
            129,
            101,
            1,
            72,
            64,
            86
          ],
          "x_position": 655,
          "y_position": 320,
          "category_name": "Best against"
        },
        {
          "width": 280,
          "height": 55,
          "hero_ids": [
            85,
            53,
            56,
            82,
            33,
            79,
            108
          ],
          "x_position": 945,
          "y_position": 320,
          "category_name": "Worst against"
        },
        {
          "width": 280,
          "height": 55,
          "hero_ids": [
            14,
            109,
            40,
            98,
            101,
            26,
            64
          ],
          "x_position": 75,
          "y_position": 395,
          "category_name": "Best with"
        },
        {
          "width": 280,
          "height": 55,
          "hero_ids": [
            145,
            22,
            105,
            63,
            39,
            101,
            53
          ],
          "x_position": 365,
          "y_position": 395,
          "category_name": "Worst with"
        },
        {
          "width": 280,
          "height": 55,
          "hero_ids": [
            7,
            129,
            87,
            123,
            53,
            46,
            14
          ],
          "x_position": 655,
          "y_position": 395,
          "category_name": "Best against"
        },
        {
          "width": 280,
          "height": 55,
          "hero_ids": [
            6,
            111,
            7,
            27,
            136,
            40,
            104
          ],
          "x_position": 945,
          "y_position": 395,
          "category_name": "Worst against"
        },
        {
          "width": 280,
          "height": 55,
          "hero_ids": [
            14,
            26,
            8,
            96,
            22,
            31,
            87
          ],
          "x_position": 75,
          "y_position": 470,
          "category_name": "Best with"
        },
        {
          "width": 280,
          "height": 55,
          "hero_ids": [
            120,
            79,
            44,
            85,
            99,
            108,
            110
          ],
          "x_position": 365,
          "y_position": 470,
          "category_name": "Worst with"
        },
        {
          "width": 280,
          "height": 55,
          "hero_ids": [
            123,
            1,
            2,
            49,
            104,
            70,
            52
          ],
          "x_position": 655,
          "y_position": 470,
          "category_name": "Best against"
        },
        {
          "width": 280,
          "height": 55,
          "hero_ids": [
            14,
            82,
            108,
            49,
            51,
            40,
            50
          ],
          "x_position": 945,
          "y_position": 470,
          "category_name": "Worst against"
        }
      ],
      "config_name": "Dota2ProTracker 7.39e - Mid"
    },
    {
      "categories": [
        {
          "width": 65,
          "height": 525,
          "hero_ids": [
            129,
            98,
            2,
            104,
            28,
            135,
            96
          ],
          "x_position": 0,
          "y_position": 0,
          "category_name": "Top Heroes Pos 3"
        },
        {
          "width": 280,
          "height": 55,
          "hero_ids": [
            50,
            27,
            82,
            52,
            14,
            45,
            106
          ],
          "x_position": 75,
          "y_position": 20,
          "category_name": "Best with"
        },
        {
          "width": 280,
          "height": 55,
          "hero_ids": [
            1,
            123,
            86,
            53,
            35,
            109,
            94
          ],
          "x_position": 365,
          "y_position": 20,
          "category_name": "Worst with"
        },
        {
          "width": 280,
          "height": 55,
          "hero_ids": [
            11,
            27,
            63,
            95,
            93,
            37,
            22
          ],
          "x_position": 655,
          "y_position": 20,
          "category_name": "Best against"
        },
        {
          "width": 280,
          "height": 55,
          "hero_ids": [
            14,
            128,
            54,
            52,
            74,
            106,
            46
          ],
          "x_position": 945,
          "y_position": 20,
          "category_name": "Worst against"
        },
        {
          "width": 280,
          "height": 55,
          "hero_ids": [
            106,
            40,
            46,
            109,
            62,
            126,
            52
          ],
          "x_position": 75,
          "y_position": 95,
          "category_name": "Best with"
        },
        {
          "width": 280,
          "height": 55,
          "hero_ids": [
            120,
            53,
            45,
            145,
            1,
            18,
            68
          ],
          "x_position": 365,
          "y_position": 95,
          "category_name": "Worst with"
        },
        {
          "width": 280,
          "height": 55,
          "hero_ids": [
            1,
            36,
            64,
            72,
            84,
            123,
            2
          ],
          "x_position": 655,
          "y_position": 95,
          "category_name": "Best against"
        },
        {
          "width": 280,
          "height": 55,
          "hero_ids": [
            70,
            30,
            48,
            40,
            52,
            87,
            45
          ],
          "x_position": 945,
          "y_position": 95,
          "category_name": "Worst against"
        },
        {
          "width": 280,
          "height": 55,
          "hero_ids": [
            40,
            126,
            74,
            6,
            45,
            52,
            109
          ],
          "x_position": 75,
          "y_position": 170,
          "category_name": "Best with"
        },
        {
          "width": 280,
          "height": 55,
          "hero_ids": [
            27,
            18,
            11,
            51,
            93,
            94,
            13
          ],
          "x_position": 365,
          "y_position": 170,
          "category_name": "Worst with"
        },
        {
          "width": 280,
          "height": 55,
          "hero_ids": [
            10,
            1,
            129,
            86,
            76,
            35,
            28
          ],
          "x_position": 655,
          "y_position": 170,
          "category_name": "Best against"
        },
        {
          "width": 280,
          "height": 55,
          "hero_ids": [
            14,
            102,
            53,
            98,
            106,
            104,
            71
          ],
          "x_position": 945,
          "y_position": 170,
          "category_name": "Worst against"
        },
        {
          "width": 280,
          "height": 55,
          "hero_ids": [
            109,
            40,
            52,
            53,
            48,
            10,
            123
          ],
          "x_position": 75,
          "y_position": 245,
          "category_name": "Best with"
        },
        {
          "width": 280,
          "height": 55,
          "hero_ids": [
            145,
            86,
            37,
            79,
            18,
            36,
            49
          ],
          "x_position": 365,
          "y_position": 245,
          "category_name": "Worst with"
        },
        {
          "width": 280,
          "height": 55,
          "hero_ids": [
            39,
            1,
            75,
            64,
            86,
            7,
            129
          ],
          "x_position": 655,
          "y_position": 245,
          "category_name": "Best against"
        },
        {
          "width": 280,
          "height": 55,
          "hero_ids": [
            105,
            53,
            102,
            137,
            19,
            120,
            128
          ],
          "x_position": 945,
          "y_position": 245,
          "category_name": "Worst against"
        },
        {
          "width": 280,
          "height": 55,
          "hero_ids": [
            84,
            123,
            27,
            47,
            40,
            31,
            106
          ],
          "x_position": 75,
          "y_position": 320,
          "category_name": "Best with"
        },
        {
          "width": 280,
          "height": 55,
          "hero_ids": [
            100,
            119,
            1,
            53,
            64,
            68,
            7
          ],
          "x_position": 365,
          "y_position": 320,
          "category_name": "Worst with"
        },
        {
          "width": 280,
          "height": 55,
          "hero_ids": [
            11,
            14,
            74,
            1,
            64,
            49,
            53
          ],
          "x_position": 655,
          "y_position": 320,
          "category_name": "Best against"
        },
        {
          "width": 280,
          "height": 55,
          "hero_ids": [
            109,
            40,
            53,
            106,
            8,
            88,
            2
          ],
          "x_position": 945,
          "y_position": 320,
          "category_name": "Worst against"
        },
        {
          "width": 280,
          "height": 55,
          "hero_ids": [
            88,
            59,
            5,
            52,
            40,
            46,
            70
          ],
          "x_position": 75,
          "y_position": 395,
          "category_name": "Best with"
        },
        {
          "width": 280,
          "height": 55,
          "hero_ids": [
            41,
            63,
            14,
            48,
            86,
            100,
            7
          ],
          "x_position": 365,
          "y_position": 395,
          "category_name": "Worst with"
        },
        {
          "width": 280,
          "height": 55,
          "hero_ids": [
            64,
            7,
            123,
            46,
            48,
            14,
            18
          ],
          "x_position": 655,
          "y_position": 395,
          "category_name": "Best against"
        },
        {
          "width": 280,
          "height": 55,
          "hero_ids": [
            40,
            27,
            51,
            64,
            71,
            7,
            8
          ],
          "x_position": 945,
          "y_position": 395,
          "category_name": "Worst against"
        },
        {
          "width": 280,
          "height": 55,
          "hero_ids": [
            62,
            31,
            14,
            53,
            8,
            26,
            87
          ],
          "x_position": 75,
          "y_position": 470,
          "category_name": "Best with"
        },
        {
          "width": 280,
          "height": 55,
          "hero_ids": [
            10,
            49,
            119,
            93,
            7,
            22,
            64
          ],
          "x_position": 365,
          "y_position": 470,
          "category_name": "Worst with"
        },
        {
          "width": 280,
          "height": 55,
          "hero_ids": [
            86,
            26,
            36,
            101,
            10,
            11,
            1
          ],
          "x_position": 655,
          "y_position": 470,
          "category_name": "Best against"
        },
        {
          "width": 280,
          "height": 55,
          "hero_ids": [
            14,
            40,
            5,
            111,
            123,
            109,
            22
          ],
          "x_position": 945,
          "y_position": 470,
          "category_name": "Worst against"
        }
      ],
      "config_name": "Dota2ProTracker 7.39e - Offlane"
    },
    {
      "categories": [
        {
          "width": 65,
          "height": 525,
          "hero_ids": [
            128,
            86,
            71,
            14,
            101,
            26,
            21
          ],
          "x_position": 0,
          "y_position": 0,
          "category_name": "Top Heroes Pos 4"
        },
        {
          "width": 280,
          "height": 55,
          "hero_ids": [
            102,
            59,
            26,
            8,
            70,
            52,
            47
          ],
          "x_position": 75,
          "y_position": 20,
          "category_name": "Best with"
        },
        {
          "width": 280,
          "height": 55,
          "hero_ids": [
            145,
            67,
            126,
            18,
            49,
            11,
            131
          ],
          "x_position": 365,
          "y_position": 20,
          "category_name": "Worst with"
        },
        {
          "width": 280,
          "height": 55,
          "hero_ids": [
            1,
            14,
            123,
            97,
            7,
            64,
            74
          ],
          "x_position": 655,
          "y_position": 20,
          "category_name": "Best against"
        },
        {
          "width": 280,
          "height": 55,
          "hero_ids": [
            22,
            52,
            40,
            137,
            71,
            41,
            8
          ],
          "x_position": 945,
          "y_position": 20,
          "category_name": "Worst against"
        },
        {
          "width": 280,
          "height": 55,
          "hero_ids": [
            14,
            56,
            50,
            137,
            136,
            111,
            3
          ],
          "x_position": 75,
          "y_position": 95,
          "category_name": "Best with"
        },
        {
          "width": 280,
          "height": 55,
          "hero_ids": [
            10,
            13,
            46,
            128,
            1,
            17,
            129
          ],
          "x_position": 365,
          "y_position": 95,
          "category_name": "Worst with"
        },
        {
          "width": 280,
          "height": 55,
          "hero_ids": [
            19,
            145,
            21,
            11,
            10,
            114,
            48
          ],
          "x_position": 655,
          "y_position": 95,
          "category_name": "Best against"
        },
        {
          "width": 280,
          "height": 55,
          "hero_ids": [
            96,
            70,
            71,
            8,
            52,
            72,
            14
          ],
          "x_position": 945,
          "y_position": 95,
          "category_name": "Worst against"
        },
        {
          "width": 280,
          "height": 55,
          "hero_ids": [
            94,
            70,
            40,
            52,
            31,
            8,
            87
          ],
          "x_position": 75,
          "y_position": 170,
          "category_name": "Best with"
        },
        {
          "width": 280,
          "height": 55,
          "hero_ids": [
            100,
            3,
            29,
            105,
            1,
            40,
            79
          ],
          "x_position": 365,
          "y_position": 170,
          "category_name": "Worst with"
        },
        {
          "width": 280,
          "height": 55,
          "hero_ids": [
            1,
            75,
            64,
            86,
            101,
            49,
            10
          ],
          "x_position": 655,
          "y_position": 170,
          "category_name": "Best against"
        },
        {
          "width": 280,
          "height": 55,
          "hero_ids": [
            111,
            68,
            14,
            27,
            74,
            102,
            6
          ],
          "x_position": 945,
          "y_position": 170,
          "category_name": "Worst against"
        },
        {
          "width": 280,
          "height": 55,
          "hero_ids": [
            96,
            128,
            102,
            109,
            87,
            126,
            27
          ],
          "x_position": 75,
          "y_position": 245,
          "category_name": "Best with"
        },
        {
          "width": 280,
          "height": 55,
          "hero_ids": [
            11,
            36,
            95,
            97,
            63,
            41,
            86
          ],
          "x_position": 365,
          "y_position": 245,
          "category_name": "Worst with"
        },
        {
          "width": 280,
          "height": 55,
          "hero_ids": [
            11,
            26,
            21,
            129,
            94,
            1,
            72
          ],
          "x_position": 655,
          "y_position": 245,
          "category_name": "Best against"
        },
        {
          "width": 280,
          "height": 55,
          "hero_ids": [
            30,
            28,
            8,
            53,
            135,
            109,
            40
          ],
          "x_position": 945,
          "y_position": 245,
          "category_name": "Worst against"
        },
        {
          "width": 280,
          "height": 55,
          "hero_ids": [
            40,
            52,
            45,
            106,
            5,
            36,
            135
          ],
          "x_position": 75,
          "y_position": 320,
          "category_name": "Best with"
        },
        {
          "width": 280,
          "height": 55,
          "hero_ids": [
            35,
            48,
            59,
            11,
            38,
            64,
            94
          ],
          "x_position": 365,
          "y_position": 320,
          "category_name": "Worst with"
        },
        {
          "width": 280,
          "height": 55,
          "hero_ids": [
            51,
            48,
            18,
            27,
            17,
            35,
            26
          ],
          "x_position": 655,
          "y_position": 320,
          "category_name": "Best against"
        },
        {
          "width": 280,
          "height": 55,
          "hero_ids": [
            123,
            96,
            40,
            49,
            71,
            52,
            53
          ],
          "x_position": 945,
          "y_position": 320,
          "category_name": "Worst against"
        },
        {
          "width": 280,
          "height": 55,
          "hero_ids": [
            45,
            40,
            53,
            14,
            68,
            8,
            96
          ],
          "x_position": 75,
          "y_position": 395,
          "category_name": "Best with"
        },
        {
          "width": 280,
          "height": 55,
          "hero_ids": [
            27,
            120,
            93,
            12,
            1,
            38,
            64
          ],
          "x_position": 365,
          "y_position": 395,
          "category_name": "Worst with"
        },
        {
          "width": 280,
          "height": 55,
          "hero_ids": [
            17,
            11,
            129,
            96,
            7,
            53,
            18
          ],
          "x_position": 655,
          "y_position": 395,
          "category_name": "Best against"
        },
        {
          "width": 280,
          "height": 55,
          "hero_ids": [
            14,
            75,
            53,
            74,
            84,
            40,
            126
          ],
          "x_position": 945,
          "y_position": 395,
          "category_name": "Worst against"
        },
        {
          "width": 280,
          "height": 55,
          "hero_ids": [
            29,
            14,
            137,
            40,
            109,
            41,
            74
          ],
          "x_position": 75,
          "y_position": 470,
          "category_name": "Best with"
        },
        {
          "width": 280,
          "height": 55,
          "hero_ids": [
            72,
            129,
            64,
            26,
            53,
            13,
            54
          ],
          "x_position": 365,
          "y_position": 470,
          "category_name": "Worst with"
        },
        {
          "width": 280,
          "height": 55,
          "hero_ids": [
            18,
            53,
            7,
            95,
            59,
            126,
            76
          ],
          "x_position": 655,
          "y_position": 470,
          "category_name": "Best against"
        },
        {
          "width": 280,
          "height": 55,
          "hero_ids": [
            98,
            106,
            104,
            28,
            71,
            52,
            14
          ],
          "x_position": 945,
          "y_position": 470,
          "category_name": "Worst against"
        }
      ],
      "config_name": "Dota2ProTracker 7.39e - Support"
    },
    {
      "categories": [
        {
          "width": 65,
          "height": 525,
          "hero_ids": [
            87,
            64,
            26,
            75,
            14,
            31,
            128
          ],
          "x_position": 0,
          "y_position": 0,
          "category_name": "Top Heroes Pos 5"
        },
        {
          "width": 280,
          "height": 55,
          "hero_ids": [
            52,
            109,
            14,
            53,
            96,
            8,
            13
          ],
          "x_position": 75,
          "y_position": 20,
          "category_name": "Best with"
        },
        {
          "width": 280,
          "height": 55,
          "hero_ids": [
            145,
            63,
            67,
            18,
            19,
            95,
            11
          ],
          "x_position": 365,
          "y_position": 20,
          "category_name": "Worst with"
        },
        {
          "width": 280,
          "height": 55,
          "hero_ids": [
            27,
            14,
            1,
            72,
            64,
            96,
            18
          ],
          "x_position": 655,
          "y_position": 20,
          "category_name": "Best against"
        },
        {
          "width": 280,
          "height": 55,
          "hero_ids": [
            74,
            53,
            14,
            106,
            22,
            111,
            40
          ],
          "x_position": 945,
          "y_position": 20,
          "category_name": "Worst against"
        },
        {
          "width": 280,
          "height": 55,
          "hero_ids": [
            54,
            106,
            36,
            76,
            94,
            60,
            74
          ],
          "x_position": 75,
          "y_position": 95,
          "category_name": "Best with"
        },
        {
          "width": 280,
          "height": 55,
          "hero_ids": [
            18,
            21,
            49,
            10,
            26,
            96,
            53
          ],
          "x_position": 365,
          "y_position": 95,
          "category_name": "Worst with"
        },
        {
          "width": 280,
          "height": 55,
          "hero_ids": [
            145,
            85,
            51,
            120,
            14,
            123,
            86
          ],
          "x_position": 655,
          "y_position": 95,
          "category_name": "Best against"
        },
        {
          "width": 280,
          "height": 55,
          "hero_ids": [
            40,
            135,
            26,
            53,
            71,
            8,
            98
          ],
          "x_position": 945,
          "y_position": 95,
          "category_name": "Worst against"
        },
        {
          "width": 280,
          "height": 55,
          "hero_ids": [
            128,
            62,
            102,
            53,
            52,
            14,
            96
          ],
          "x_position": 75,
          "y_position": 170,
          "category_name": "Best with"
        },
        {
          "width": 280,
          "height": 55,
          "hero_ids": [
            120,
            21,
            86,
            49,
            114,
            22,
            63
          ],
          "x_position": 365,
          "y_position": 170,
          "category_name": "Worst with"
        },
        {
          "width": 280,
          "height": 55,
          "hero_ids": [
            64,
            38,
            51,
            129,
            1,
            128,
            18
          ],
          "x_position": 655,
          "y_position": 170,
          "category_name": "Best against"
        },
        {
          "width": 280,
          "height": 55,
          "hero_ids": [
            96,
            126,
            48,
            109,
            46,
            14,
            59
          ],
          "x_position": 945,
          "y_position": 170,
          "category_name": "Worst against"
        },
        {
          "width": 280,
          "height": 55,
          "hero_ids": [
            27,
            96,
            106,
            53,
            71,
            104,
            126
          ],
          "x_position": 75,
          "y_position": 245,
          "category_name": "Best with"
        },
        {
          "width": 280,
          "height": 55,
          "hero_ids": [
            35,
            41,
            72,
            11,
            54,
            21,
            10
          ],
          "x_position": 365,
          "y_position": 245,
          "category_name": "Worst with"
        },
        {
          "width": 280,
          "height": 55,
          "hero_ids": [
            26,
            120,
            18,
            11,
            17,
            129,
            21
          ],
          "x_position": 655,
          "y_position": 245,
          "category_name": "Best against"
        },
        {
          "width": 280,
          "height": 55,
          "hero_ids": [
            53,
            104,
            71,
            27,
            128,
            59,
            126
          ],
          "x_position": 945,
          "y_position": 245,
          "category_name": "Worst against"
        },
        {
          "width": 280,
          "height": 55,
          "hero_ids": [
            102,
            96,
            40,
            7,
            74,
            6,
            12
          ],
          "x_position": 75,
          "y_position": 320,
          "category_name": "Best with"
        },
        {
          "width": 280,
          "height": 55,
          "hero_ids": [
            1,
            18,
            26,
            10,
            36,
            47,
            135
          ],
          "x_position": 365,
          "y_position": 320,
          "category_name": "Worst with"
        },
        {
          "width": 280,
          "height": 55,
          "hero_ids": [
            86,
            76,
            18,
            48,
            75,
            94,
            11
          ],
          "x_position": 655,
          "y_position": 320,
          "category_name": "Best against"
        },
        {
          "width": 280,
          "height": 55,
          "hero_ids": [
            40,
            128,
            87,
            13,
            7,
            64,
            135
          ],
          "x_position": 945,
          "y_position": 320,
          "category_name": "Worst against"
        },
        {
          "width": 280,
          "height": 55,
          "hero_ids": [
            88,
            96,
            109,
            8,
            53,
            14,
            71
          ],
          "x_position": 75,
          "y_position": 395,
          "category_name": "Best with"
        },
        {
          "width": 280,
          "height": 55,
          "hero_ids": [
            6,
            95,
            67,
            87,
            11,
            19,
            114
          ],
          "x_position": 365,
          "y_position": 395,
          "category_name": "Worst with"
        },
        {
          "width": 280,
          "height": 55,
          "hero_ids": [
            18,
            35,
            36,
            72,
            5,
            40,
            26
          ],
          "x_position": 655,
          "y_position": 395,
          "category_name": "Best against"
        },
        {
          "width": 280,
          "height": 55,
          "hero_ids": [
            6,
            111,
            75,
            52,
            106,
            7,
            126
          ],
          "x_position": 945,
          "y_position": 395,
          "category_name": "Worst against"
        },
        {
          "width": 280,
          "height": 55,
          "hero_ids": [
            126,
            14,
            7,
            17,
            26,
            54,
            8
          ],
          "x_position": 75,
          "y_position": 470,
          "category_name": "Best with"
        },
        {
          "width": 280,
          "height": 55,
          "hero_ids": [
            119,
            86,
            62,
            95,
            60,
            53,
            38
          ],
          "x_position": 365,
          "y_position": 470,
          "category_name": "Worst with"
        },
        {
          "width": 280,
          "height": 55,
          "hero_ids": [
            48,
            129,
            1,
            46,
            53,
            94,
            11
          ],
          "x_position": 655,
          "y_position": 470,
          "category_name": "Best against"
        },
        {
          "width": 280,
          "height": 55,
          "hero_ids": [
            63,
            70,
            14,
            54,
            102,
            104,
            87
          ],
          "x_position": 945,
          "y_position": 470,
          "category_name": "Worst against"
        }
      ],
      "config_name": "Dota2ProTracker 7.39e - Hard Support"
    }
  ],
  "version": 3
}